setup.py
lokliner/__init__.py
lokliner/smoother.py
lokliner/snapper.py
lokliner.egg-info/PKG-INFO
lokliner.egg-info/SOURCES.txt
lokliner.egg-info/dependency_links.txt
lokliner.egg-info/not-zip-safe
lokliner.egg-info/requires.txt
lokliner.egg-info/top_level.txt