Metadata-Version: 1.0
Name: lokliner
Version: 0.1.0
Summary: Smoothing routes
Home-page: https://github.com/ankushpatel/lokliner.git
Author: Ankush Patel
Author-email: ankush@loktra.com
License: MIT
Platform: UNKNOWN
